botocore/__init__.py
botocore/args.py
botocore/auth.py
botocore/awsrequest.py
botocore/cacert.pem
botocore/client.py
botocore/compat.py
botocore/compress.py
botocore/config.py
botocore/configloader.py
botocore/configprovider.py
botocore/credentials.py
botocore/discovery.py
botocore/endpoint.py
botocore/endpoint_provider.py
botocore/errorfactory.py
botocore/eventstream.py
botocore/exceptions.py
botocore/handlers.py
botocore/history.py
botocore/hooks.py
botocore/httpchecksum.py
botocore/httpsession.py
botocore/loaders.py
botocore/model.py
botocore/monitoring.py
botocore/paginate.py
botocore/parsers.py
botocore/regions.py
botocore/response.py
botocore/retryhandler.py
botocore/serialize.py
botocore/session.py
botocore/signers.py
botocore/stub.py
botocore/tokens.py
botocore/translate.py
botocore/useragent.py
botocore/utils.py
botocore/validate.py
botocore/waiter.py
botocore/crt/__init__.py
botocore/crt/auth.py
botocore/data/_retry.json
botocore/data/endpoints.json
botocore/data/partitions.json
botocore/data/sdk-default-configuration.json
botocore/docs/__init__.py
botocore/docs/client.py
botocore/docs/docstring.py
botocore/docs/example.py
botocore/docs/method.py
botocore/docs/paginator.py
botocore/docs/params.py
botocore/docs/service.py
botocore/docs/shape.py
botocore/docs/sharedexample.py
botocore/docs/translator.py
botocore/docs/utils.py
botocore/docs/waiter.py
botocore/docs/bcdoc/__init__.py
botocore/docs/bcdoc/docstringparser.py
botocore/docs/bcdoc/restdoc.py
botocore/docs/bcdoc/style.py
botocore/retries/__init__.py
botocore/retries/adaptive.py
botocore/retries/base.py
botocore/retries/bucket.py
botocore/retries/quota.py
botocore/retries/special.py
botocore/retries/standard.py
botocore/retries/throttling.py
botocore/vendored/__init__.py
botocore/vendored/six.py
botocore/vendored/requests/__init__.py
botocore/vendored/requests/exceptions.py
botocore/vendored/requests/packages/__init__.py
botocore/vendored/requests/packages/urllib3/__init__.py
botocore_a_la_carte-1.34.144.dist-info/LICENSE.txt
botocore_a_la_carte-1.34.144.dist-info/METADATA
botocore_a_la_carte-1.34.144.dist-info/NOTICE
botocore_a_la_carte-1.34.144.dist-info/WHEEL
botocore_a_la_carte-1.34.144.dist-info/top_level.txt
botocore_a_la_carte-1.34.144.dist-info/RECORD
