Metadata-Version: 2.1
Name: botocore-a-la-carte
Version: 1.34.144
Summary: botocore re-uploaded with a-la-carte data packages.
Home-page: https://github.com/thejcannon/botocore-a-la-carte
Author: Amazon Web Services
License: Apache License 2.0
Platform: UNKNOWN
Classifier: Development Status :: 5 - Production/Stable
Classifier: Intended Audience :: Developers
Classifier: Intended Audience :: System Administrators
Classifier: Natural Language :: English
Classifier: License :: OSI Approved :: Apache Software License
Classifier: Programming Language :: Python
Classifier: Programming Language :: Python :: 3 :: Only
Classifier: Programming Language :: Python :: 3
Classifier: Programming Language :: Python :: 3.8
Classifier: Programming Language :: Python :: 3.9
Classifier: Programming Language :: Python :: 3.10
Classifier: Programming Language :: Python :: 3.11
Classifier: Programming Language :: Python :: 3.12
Requires-Python: >= 3.8
License-File: LICENSE.txt
License-File: NOTICE
Requires-Dist: jmespath (<2.0.0,>=0.7.1)
Requires-Dist: python-dateutil (<3.0.0,>=2.1)
Requires-Dist: urllib3 (<1.27,>=1.25.4) ; python_version < "3.10"
Requires-Dist: urllib3 (!=2.2.0,<3,>=1.25.4) ; python_version >= "3.10"
Provides-Extra: crt
Requires-Dist: awscrt (==0.20.11) ; extra == 'crt'
